{
  "template": {
    "mappings": {
      "properties": {
        "employer": {
          "properties": {
            "sourceId": {
              "type": "keyword"
            },
            "source": {
              "type": "keyword"
            },
            "username": {
              "type": "keyword"
            },
            "location": {
              "properties": {
                "country": {
                  "properties": {
                    "id": {
                      "type": "keyword"
                    },
                    "name": {
                      "type": "keyword"
                    },
                    "officialName": {
                      "type": "keyword"
                    },
                    "alpha2Code": {
                      "type": "keyword"
                    },
                    "alpha3Code": {
                      "type": "keyword"
                    },
                    "numeric": {
                      "type": "keyword"
                    },
                    "region": {
                      "type": "keyword"
                    },
                    "subregion": {
                      "type": "keyword"
                    },
                    "continents": {
                      "type": "keyword"
                    },
                    "startOfWeek": {
                      "type": "keyword"
                    },
                    "coordinates": {
                      "type": "geo_point"
                    },
                    "timezones": {
                      "type": "keyword"
                    }
                  }
                },
                "city": {
                  "properties": {
                    "id": {
                      "type": "keyword"
                    },
                    "name": {
                      "type": "keyword"
                    },
                    "coordinates": {
                      "type": "geo_point"
                    }
                  }
                }
              }
            },
            "primaryLanguage": {
              "properties": {
                "id": {
                  "type": "keyword"
                },
                "shortName": {
                  "type": "keyword"
                },
                "names": {
                  "type": "keyword"
                }
              }
            },
            "primaryCurrency": {
              "properties": {
                "id": {
                  "type": "keyword"
                },
                "name": {
                  "type": "keyword"
                },
                "shortName": {
                  "type": "keyword"
                },
                "numeric": {
                  "type": "keyword"
                },
                "precision": {
                  "type": "integer"
                },
                "countries": {
                  "type": "keyword"
                }
              }
            },
            "timezone": {
              "properties": {
                "id": {
                  "type": "keyword"
                },
                "name": {
                  "type": "keyword"
                },
                "abbreviation": {
                  "type": "keyword"
                },
                "utcOffset": {
                  "type": "keyword"
                },
                "utcOffsetRaw": {
                  "type": "long"
                }
              }
            }
          }
        }
      }
    }
  },
  "version": 2,
  "_meta": {
    "description": "Employer mapping"
  }
}